CodeDrive/Functions.py
CodeDrive/__init__.py
CodeDrive-1.8.dist-info/LICENSE.txt
CodeDrive-1.8.dist-info/METADATA
CodeDrive-1.8.dist-info/WHEEL
CodeDrive-1.8.dist-info/top_level.txt
CodeDrive-1.8.dist-info/RECORD
