Metadata-Version: 2.1
Name: CodeDrive
Version: 1.8
Summary: This package contains codes/functions that are useful in school level python programming
Home-page: https://github.com/Stark-Corp/CodeDrive
Author: Stark-Corp (Himangshu De)
Author-email: dehimangshu2020@gmail.com
License: UNKNOWN
Keywords: python,school level programs,beginners
Platform: UNKNOWN
Classifier: Development Status :: 1 - Planning
Classifier: Intended Audience :: Education
Classifier: License :: OSI Approved :: MIT License
Classifier: Programming Language :: Python :: 3
Classifier: Operating System :: OS Independent
Requires-Python: >=3.0
